taichu_dataflow/__init__.py
taichu_dataflow/command.py
taichu_dataflow/export_back.py
taichu_dataflow/storage/__init__.py
taichu_dataflow/storage/alluxio.py
taichu_dataflow/storage/env.py
taichu_dataflow/storage/obs.py
taichu_dataflow-1.1.2.dist-info/METADATA
taichu_dataflow-1.1.2.dist-info/WHEEL
taichu_dataflow-1.1.2.dist-info/entry_points.txt
taichu_dataflow-1.1.2.dist-info/top_level.txt
taichu_dataflow-1.1.2.dist-info/RECORD
