Metadata-Version: 2.1
Name: taichu-dataflow
Version: 1.1.2
Summary: taichu serve is a tool for serving dataflow
Home-page: UNKNOWN
Author: taichu platform team
License: UNKNOWN
Keywords: taichu
Platform: UNKNOWN
Requires-Python: >=3.6.0
Requires-Dist: boto (==2.49.0)
Requires-Dist: esdk-obs-python (==3.22.2)
Requires-Dist: click (==8.1.3)
